{
  "_id": "5279JHh7N7k",
  "videoSnippet": {
    "schemaVersion": 1,
    "retrievedAt": "2025-05-27T20:31:24.674Z",
    "publishedAt": "2025-05-27T20:15:50Z",
    "title": "Hikaru vs Magnus || Norway Chess 2025 (A)",
    "description": "Search all my videos easy https://agadmator-library.github.io/\n\n0:00 Hello Everyone!\n01:00  Game Starts!\n10:50 IWITP\n12:00 Legends of the Channel\n\nNakamura, Hikaru (2837) - Carlsen, Magnus (2883) \nNorway Chess 2025 (Chess.com) [04] 2025.05.27\nD78 Neo-Gruenfeld, 6.O-O c6\n\n1.Nf3 d5 2.g3 g6 3.d4 Bg7 4.Bg2 Nf6 5.O-O O-O 6.c4 c6 7.Qb3 dxc4 8.Qxc4 Bf5 9.Nc3 Nbd7 10.Bf4 Nb6 11.Qb3 Nfd5 12.Be5 Nxc3 13.bxc3 Be4 14.Bxg7 Kxg7 15.Rac1 c5 16.dxc5 Nd7 17.Qb4 Nf6 18.Bh3 Qc7 19.Nd4 b6 20.cxb6 axb6 21.Qb2 Ra4 22.Be6 Ra5 23.Bb3 e5 24.Nc2 h5 25.h4 Ng4 26.Na3 g5 27.Nc4 gxh4 28.f3 Qc5+ 29.Kh1 Ba8 30.Nxa5 bxa5 31.e4 hxg3 32.Bd5 Bxd5 33.exd5 Ne3 34.Rg1 h4 35.c4 Qd4 36.Qxd4 exd4 37.d6 Rb8 38.Rb1 Rd8 39.c5 Kf6 40.c6 Rxd6 41.c7 Rc6 42.Rgc1 Nc4 43.Rb6 Rxb6 44.c8=Q\n\nCheck out agadmator's merch here https://teespring.com/stores/agadmators-swag-store\nhttps://teespring.com/design-with-a-story-tm\n\nMailbox where you can send stuff:\n\nAntonio Radić\nAGADMATOR d.o.o.\nFranje Tuđmana 12\nCroatia\n48260 Križevci \np.s. this is not my home address :)\n\nContact me: agadmator@gmail.com \n\nVideo created by OBS\n\n----------------------------------------------------------------------------------------------------------------------------------------\nIf you realllly enjoy my content, you're welcome to support me and my channel with a small donation via PayPal or Crypto.\n\nLink to PayPal donation https://www.paypal.me/agadmator\n\nMaiar Wallet @agadmator or join me here https://get.maiar.com/referral/pv0mam6l2a\nBTC address bc1qckd3ut0hqyymzv33eus97ld8klj02xhk2kcwld\nBCH address qzmfclyn69hqhjslls40r7r0dsttwe3tcsl946w4fr\nLTC address Laarf1RmvCpLt2BcSwC1PBLG3hRC4HjBrz\nNANO nano_1h1kgfaq88t1btwadqzx73rbha5hwbb88sxmfns851kwj8hnosdj51w388xx\nMonero 4AdvvqmC4xhPyyRSAEDxTTAoXdxAtX2Py6b8Eh4EQzBLGbgo5rY5Khcap1x76JrDJH87yibAE9b6TPwTsvBAiFFCLtM8Be7\nFor any other currency address, contact me via agadmator@gmail.com\n\nCheck out some of the books I enjoy https://www.amazon.com/ideas/amzn1.account.AFWWCIBWCL5PGEPL73FDWK632F7Q/2QAGBMLVXE7MG\n\nCheck out ALL my videos here https://www.youtube.com/watch?v=fYgd5ZLdHz8&list=PLDnx7w_xuguFTxcfiM11bB1JchtHclEJg\n\nFacebook: https://www.facebook.com/agadmatoryoutube\nTwitter: https://twitter.com/agadmator\nInstagram: https://www.instagram.com/agadmator/\nLichess: https://lichess.org/@/agadmator\nChess.com: agadmator\nLeague of Legends: agadmator (EUNE, my friend is using my EUWE account for a couple of years now)\nBlizzard: agadmator #2992 \nJoin our Discord Server here https://discord.gg/bY6BbRP\n\n#youareawesome \"Watch me without ads on your Amazon devices (https://bit.ly/Agadmator_Amazon) and Roku TV (https://bit.ly/Agadmator_Roku)",
    "thumbnail": {
      "default": {
        "url": "https://i.ytimg.com/vi/5279JHh7N7k/default.jpg",
        "width": 120,
        "height": 90
      },
      "medium": {
        "url": "https://i.ytimg.com/vi/5279JHh7N7k/mqdefault.jpg",
        "width": 320,
        "height": 180
      },
      "high": {
        "url": "https://i.ytimg.com/vi/5279JHh7N7k/hqdefault.jpg",
        "width": 480,
        "height": 360
      },
      "standard": {
        "url": "https://i.ytimg.com/vi/5279JHh7N7k/sddefault.jpg",
        "width": 640,
        "height": 480
      },
      "maxres": {
        "url": "https://i.ytimg.com/vi/5279JHh7N7k/maxresdefault.jpg",
        "width": 1280,
        "height": 720
      }
    },
    "videoId": "5279JHh7N7k"
  },
  "videoContentDetails": {
    "duration": "PT12M21S"
  },
  "videoGame": [
    {
      "pgn": "1. Nf3 d5 2. g3 g6 3. d4 Bg7 4. Bg2 Nf6 5. O-O O-O 6. c4 c6 7. Qb3 dxc4 8. Qxc4 Bf5 9. Nc3 Nbd7 10. Bf4 Nb6 11. Qb3 Nfd5 12. Be5 Nxc3 13. bxc3 Be4 14. Bxg7 Kxg7 15. Rac1 c5 16. dxc5 Nd7 17. Qb4 Nf6 18. Bh3 Qc7 19. Nd4 b6 20. cxb6 axb6 21. Qb2 Ra4 22. Be6 Ra5 23. Bb3 e5 24. Nc2 h5 25. h4 Ng4 26. Na3 g5 27. Nc4 gxh4 28. f3 Qc5+ 29. Kh1 Ba8 30. Nxa5 bxa5 31. e4 hxg3 32. Bd5 Bxd5 33. exd5 Ne3 34. Rg1 h4 35. c4 Qd4 36. Qxd4 exd4 37. d6 Rb8 38. Rb1 Rd8 39. c5 Kf6 40. c6 Rxd6 41. c7 Rc6 42. Rgc1 Nc4 43. Rb6 Rxb6 44. c8=Q",
      "fen": "2Q5/5p2/1r3k2/p7/2np3p/5Pp1/P7/2R4K b - - 0 1",
      "playerWhite": "Hikaru Nakamura",
      "playerBlack": "Magnus Carlsen",
      "date": "2025-05-27"
    }
  ],
  "chessCom": {
    "reason": "NOT_FOUND",
    "retrievedAt": "2025-05-27T20:31:25.071Z"
  },
  "chesstempoCom": {
    "reason": "NOT_FOUND",
    "retrievedAt": "2025-05-27T20:31:25.656Z"
  },
  "chess365": {
    "reason": "NOT_FOUND",
    "retrievedAt": "2025-05-27T20:31:26.333Z"
  },
  "lichessMasters": {
    "reason": "NOT_FOUND",
    "retrievedAt": "2025-05-27T20:31:26.930Z"
  },
  "lichessGameId": [
    {
      "id": "YS2I1ETI"
    }
  ],
  "stockfishEval": [
    {
      "cp": -937,
      "mate": null
    }
  ]
}