{
  "_id": "BmXoSdl1ryg",
  "videoSnippet": {
    "schemaVersion": 1,
    "retrievedAt": "2023-02-12T19:40:51.240Z",
    "publishedAt": "2021-02-12T20:45:30Z",
    "title": "Better Movie Ending Than Armageddon",
    "description": "New Channel here https://www.youtube.com/channel/UCCVGy0TLDdeXszpqJw7FhJQ/\nEmail where you can contact me regarding the other channel: excellentsubscribers@gmail.com\n\nMagnus Carlsen vs Maxime Vachier Lagrave\nOpera Euro Rapid, Semifinals Game 7, Feb-11\nGruenfeld, exchange variation (D85)\n\n1. d4 Nf6 2. c4 g6 3. Nc3 d5 4. cxd5 Nxd5 5. Bd2 Bg7 6. e4 Nb6 7. Be3 O-O 8. a4 a5 9. h3 Nc6 10. Nf3 f5 11. exf5 Bxf5 12. Be2 Nb4 13. Rc1 c6 14. O-O N6d5 15. Bd2 Qd6 16. Re1 Kh8 17. Nxd5 Nxd5 18. Bc4 Nb4 19. Qb3 Rad8 20. Bg5 Bf6 21. Bh6 Bg7 22. Qe3 Rde8 23. Bf4 Nd5 24. Bxd5 Qxd5 25. Rc5 Qd8 26. Be5 Bc8 27. Qh6 Rf6 28. Bxf6 exf6 29. Rxe8+ Qxe8 30. Qe3 Qd8 31. Qe1 Bf8 32. Rxa5 Bd7 33. Ra7 Qb8 34. Qa5 Kg7 35. Ra8 Qf4 36. Qd8 Qc1+ 37. Kh2 Qf4+ 38. Kh1 Qd6 39. Qb8 Qb4 40. Ra7\n\nWorld Chess Champion Magnus Carlsen tops the field for the Opera Euro Rapid, the 3rd stage of the Meltwater Champions Chess Tour. The 16-player event will be played online on chess24 from February 6th to 14th and features a $100,000 prize fund, with $30,000 for 1st place.\n\nThe tournament starts with a 3-day all-play-all preliminary stage before the top 8 go forward to a knockout. The time control is 15 minutes for all moves, with a 10-second increment from move 1. No draw offers are allowed before move 40. Official website: championschesstour.com\n\nCheck out agadmator's merch here https://teespring.com/stores/agadmators-swag-store\nhttps://teespring.com/design-with-a-story-tm\n\nMailbox where you can send stuff:\n\nAntonio Radić\nAGADMATOR d.o.o.\nFranje Tuđmana 12\nCroatia\n48260 Križevci \np.s. this is not my home address :)\n\nContact me: agadmatormanga@gmail.com or agadmator@gmail.com \n\nDownload agadmator chess clock for iOS here https://apps.apple.com/us/app/agadmator-chess-clock/id1474461379?ls=1&fbclid=IwAR2lhuxf60tpbW1vcvfXgdFzmShi6fHcrKxFF_NAhu9wLQwpJrAFbMWRYjk\n\nDownload agadmator chess clock for Android here https://play.google.com/store/Qapps/details?id=com.agadmator.chessclock&fbclid=IwAR3b_sRch6nsuW59-bWoirVDMMJ8V5jexZdUB0bsxQrc0Q8imvkBtqkHUXQ&rdid=com.agadmator.chessclock\n\nVideo created by OBS\n\n----------------------------------------------------------------------------------------------------------------------------------------\nIf you realllly enjoy my content, you're welcome to support me and my channel with a small donation via PayPal or Crypto.\n\nLink to PayPal donation https://www.paypal.me/agadmator\n\nMaiar Wallet @agadmator or https://get.maiar.com/referral/pv0mam6l2a\nBTC address bc1qckd3ut0hqyymzv33eus97ld8klj02xhk2kcwld\nBCH address qzmfclyn69hqhjslls40r7r0dsttwe3tcsl946w4fr\nLTC address Laarf1RmvCpLt2BcSwC1PBLG3hRC4HjBrz\n\nNANO nano_1h1kgfaq88t1btwadqzx73rbha5hwbb88sxmfns851kwj8hnosdj51w388xx\nMonero 4AdvvqmC4xhPyyRSAEDxTTAoXdxAtX2Py6b8Eh4EQzBLGbgo5rY5Khcap1x76JrDJH87yibAE9b6TPwTsvBAiFFCLtM8Be7\nFor any other currency address, contact me via agadmator@gmail.com\n\nCheck out some of the books I enjoy https://www.amazon.com/ideas/amzn1.account.AFWWCIBWCL5PGEPL73FDWK632F7Q/2QAGBMLVXE7MG\n\nCheck out ALL my videos here https://www.youtube.com/watch?v=fYgd5ZLdHz8&list=PLDnx7w_xuguFTxcfiM11bB1JchtHclEJg\n\nFacebook: https://www.facebook.com/agadmatoryoutube\nTwitter: https://twitter.com/agadmator\nInstagram: https://www.instagram.com/agadmator/\nLichess: https://lichess.org/@/agadmator\nChess.com: agadmator\nLeague of Legends: agadmator (EUNE, my friend is using my EUWE account for a couple of years now)\nJoin our Discord Server here https://discord.gg/bY6BbRP\n\n#chesschamps",
    "thumbnail": {
      "default": {
        "url": "https://i.ytimg.com/vi/BmXoSdl1ryg/default.jpg",
        "width": 120,
        "height": 90
      },
      "medium": {
        "url": "https://i.ytimg.com/vi/BmXoSdl1ryg/mqdefault.jpg",
        "width": 320,
        "height": 180
      },
      "high": {
        "url": "https://i.ytimg.com/vi/BmXoSdl1ryg/hqdefault.jpg",
        "width": 480,
        "height": 360
      },
      "standard": {
        "url": "https://i.ytimg.com/vi/BmXoSdl1ryg/sddefault.jpg",
        "width": 640,
        "height": 480
      },
      "maxres": {
        "url": "https://i.ytimg.com/vi/BmXoSdl1ryg/maxresdefault.jpg",
        "width": 1280,
        "height": 720
      }
    },
    "videoId": "BmXoSdl1ryg"
  },
  "videoGame": {
    "pgn": "1. d4 Nf6 2. c4 g6 3. Nc3 d5 4. cxd5 Nxd5 5. Bd2 Bg7 6. e4 Nb6 7. Be3 O-O 8. a4 a5 9. h3 Nc6 10. Nf3 f5 11. exf5 Bxf5 12. Be2 Nb4 13. Rc1 c6 14. O-O N6d5 15. Bd2 Qd6 16. Re1 Kh8 17. Nxd5 Nxd5 18. Bc4 Nb4 19. Qb3 Rad8 20. Bg5 Bf6 21. Bh6 Bg7 22. Qe3 Rde8 23. Bf4 Nd5 24. Bxd5 Qxd5 25. Rc5 Qd8 26. Be5 Bc8 27. Qh6 Rf6 28. Bxf6 exf6 29. Rxe8+ Qxe8 30. Qe3 Qd8 31. Qe1 Bf8 32. Rxa5 Bd7 33. Ra7 Qb8 34. Qa5 Kg7 35. Ra8 Qf4 36. Qd8 Qc1+ 37. Kh2 Qf4+ 38. Kh1 Qd6 39. Qb8 Qb4 40. Ra7  ",
    "fen": "1Q3b2/Rp1b2kp/2p2pp1/8/Pq1P4/5N1P/1P3PP1/7K b - - 0 1",
    "playerWhite": "Magnus Carlsen",
    "playerBlack": "Maxime Vachier-Lagrave"
  },
  "chessCom": {
    "retrievedAt": "2023-02-12T11:06:32.759Z",
    "href": "https://www.chess.com/games/view/15792953",
    "playerWhite": "Magnus Carlsen",
    "playerBlack": "Maxime Vachier-Lagrave",
    "result": "1-0",
    "movesCount": "40",
    "year": "2021"
  },
  "chesstempoCom": {
    "retrievedAt": "2023-02-12T13:48:47.663Z",
    "id": 5031311,
    "playerWhite": "Carlsen, Magnus",
    "playerBlack": "Vachier-Lagrave, Maxime",
    "result": "w",
    "movesCount": 79,
    "date": "2021.2.12",
    "site": "chess24.com INT",
    "event": "Opera Euro Rapid KO 2021",
    "round": "2.33",
    "eco": "D85",
    "openingName": "Gruenfeld Defense:Exchange Variation::"
  }
}