{
  "_id": "bPFCasdNcQU",
  "videoSnippet": {
    "schemaVersion": 1,
    "retrievedAt": "2023-02-12T19:40:57.494Z",
    "publishedAt": "2019-07-07T18:23:19Z",
    "title": "Super Grandmaster Title? || Carlsen vs MVL || Croatia Grand Chess Tour (2019)",
    "description": "Kasparov vs my nephew game here https://www.youtube.com/watch?v=1IAkc691Vtw\n\nFollow Lennart Ootes https://twitter.com/LennartOotes\nhttps://www.instagram.com/lennartootes/\n\nDownload agadmator chess clock here https://play.google.com/store/apps/details?id=com.agadmator.chessclock&fbclid=IwAR3b_sRch6nsuW59-bWoirVDMMJ8V5jexZdUB0bsxQrc0Q8imvkBtqkHUXQ&rdid=com.agadmator.chessclock\n\nFollow me on Instagram for extra content https://www.instagram.com/agadmator/\n\nMagnus Carlsen vs Maxime Vachier Lagrave\nGCT Croatia (2019), rd 11, Jul-07 \nGrünfeld Defense (D70)\n\n1. d4 Nf6 2. c4 g6 3. Nc3 d5 4. Nf3 Bg7 5. cxd5 Nxd5 6. e4 Nxc3 7. bxc3 c5 8. Be3 Qa5 9. Qd2 Nc6 10. Rb1 cxd4 11. cxd4 O-O 12. Qxa5 Nxa5 13. Bd3 Bg4 14. O-O Bxf3 15. gxf3 e6 16. Rfd1 Rfd8 17. Bf1 b6 18. Ba6 Rd6 19. Rbc1 Rad8 20. Bg5 f6 21. Be3 h6 22. Bb5 f5 23. d5 g5 24. Bd2 fxe4 25. fxe4 a6 26. Ba4 exd5 27. Bb4 Re6 28. Rxd5 Rxd5 29. exd5 Re4 30. Rc8+ Kf7 31. a3 Be5 32. Be8+ Kg7 33. d6 Rd4 34. d7 Nb7 35. Be7 Re4 36. Rc6 Bd4 37. Rc7\n\nThe 2019 Croatia Grand Chess Tour is a 12-player classical all-play-all tournament taking place from 26 June to 8 July 2019 in the Novinarski Dom in Zagreb, Croatia. Magnus Carlsen and all the regular tour players will compete for a prize fund of $325,000, with $90,000 for first place.\n\nPlayers receive 130 minutes for the entire game, with a 30-second delay from move one. In case of a tie for first, rapid and, if necessary, blitz playoffs will be held on 8 July. The event is organised in partnership with Chess Club e4 from Zagreb. Official website: grandchesstour.org\n\nTo those of you who read the description: You are an excellent subscriber! :)\n\nCheck out agadmator's merch here https://teespring.com/stores/agadmators-swag-store\nhttps://teespring.com/design-with-a-story-tm\n\nVideo created by OBS\n\n----------------------------------------------------------------------------------------------------------------------------------------\nIf you realllly enjoy my content, you're welcome to support me and my channel with a small donation via PayPal or Crypto.\n\nLink to PayPal donation https://www.paypal.me/agadmator\n\nMaiar Wallet @agadmator or https://get.maiar.com/referral/pv0mam6l2a\nBTC address bc1qckd3ut0hqyymzv33eus97ld8klj02xhk2kcwld\nBCH address qzmfclyn69hqhjslls40r7r0dsttwe3tcsl946w4fr\nLTC address Laarf1RmvCpLt2BcSwC1PBLG3hRC4HjBrz\n\nNANO nano_1h1kgfaq88t1btwadqzx73rbha5hwbb88sxmfns851kwj8hnosdj51w388xx\nMonero 4AdvvqmC4xhPyyRSAEDxTTAoXdxAtX2Py6b8Eh4EQzBLGbgo5rY5Khcap1x76JrDJH87yibAE9b6TPwTsvBAiFFCLtM8Be7\nFor any other currency address, contact me via agadmator@gmail.com\n\nCheck out some of the books I enjoy https://www.amazon.com/ideas/amzn1.account.AFWWCIBWCL5PGEPL73FDWK632F7Q/2QAGBMLVXE7MG\n\nCheck out ALL my videos here https://www.youtube.com/watch?v=fYgd5ZLdHz8&list=PLDnx7w_xuguFTxcfiM11bB1JchtHclEJg\n\nSteemit: https://steemit.com/@agadmator/\nFacebook: https://www.facebook.com/agadmatoryoutube\nTwitter: https://twitter.com/agadmator\nInstagram: https://www.instagram.com/agadmator/\nLichess: https://lichess.org/@/agadmator\nChess.com: agadmator\nLeague of Legends: agadmator (EUNE, my friend is using my EUWE account for a couple of years now)\nBlizzard: agadmator #2992 \nCheck out my Hearthstone channel here https://www.youtube.com/channel/UCDKefsd8PMI0FXHwPi5yscg\n\nCheck out the SUBSCRIBERS VIDEO https://www.youtube.com/watch?v=p-xa0SkpIiA\n\n#GrandChessTour",
    "thumbnail": {
      "default": {
        "url": "https://i.ytimg.com/vi/bPFCasdNcQU/default.jpg",
        "width": 120,
        "height": 90
      },
      "medium": {
        "url": "https://i.ytimg.com/vi/bPFCasdNcQU/mqdefault.jpg",
        "width": 320,
        "height": 180
      },
      "high": {
        "url": "https://i.ytimg.com/vi/bPFCasdNcQU/hqdefault.jpg",
        "width": 480,
        "height": 360
      },
      "standard": {
        "url": "https://i.ytimg.com/vi/bPFCasdNcQU/sddefault.jpg",
        "width": 640,
        "height": 480
      },
      "maxres": {
        "url": "https://i.ytimg.com/vi/bPFCasdNcQU/maxresdefault.jpg",
        "width": 1280,
        "height": 720
      }
    },
    "videoId": "bPFCasdNcQU"
  },
  "videoGame": [
    {
      "pgn": "1. d4 Nf6 2. c4 g6 3. Nc3 d5 4. Nf3 Bg7 5. cxd5 Nxd5 6. e4 Nxc3 7. bxc3 c5 8. Be3 Qa5 9. Qd2 Nc6 10. Rb1 cxd4 11. cxd4 O-O 12. Qxa5 Nxa5 13. Bd3 Bg4 14. O-O Bxf3 15. gxf3 e6 16. Rfd1 Rfd8 17. Bf1 b6 18. Ba6 Rd6 19. Rbc1 Rad8 20. Bg5 f6 21. Be3 h6 22. Bb5 f5 23. d5 g5 24. Bd2 fxe4 25. fxe4 a6 26. Ba4 exd5 27. Bb4 Re6 28. Rxd5 Rxd5 29. exd5 Re4 30. Rc8+ Kf7 31. a3 Be5 32. Be8+ Kg7 33. d6 Rd4 34. d7 Nb7 35. Be7 Re4 36. Rc6 Bd4 37. Rc7  ",
      "fen": "4B3/1nRPB1k1/pp5p/6p1/3br3/P7/5P1P/6K1 b - - 0 1",
      "playerWhite": "Magnus Carlsen",
      "playerBlack": "Maxime Vachier-Lagrave"
    }
  ],
  "chessCom": {
    "retrievedAt": "2023-02-12T15:15:26.950Z",
    "href": "https://www.chess.com/games/view/15609201",
    "playerWhite": "Magnus Carlsen",
    "playerBlack": "Maxime Vachier-Lagrave",
    "result": "1-0",
    "movesCount": "37",
    "year": "2019"
  },
  "chesstempoCom": {
    "retrievedAt": "2023-02-12T16:20:31.996Z",
    "id": 4717313,
    "playerWhite": "Carlsen, Magnus",
    "playerBlack": "Vachier-Lagrave, Maxime",
    "result": "w",
    "movesCount": 73,
    "date": "2019.7.7",
    "site": "Zagreb CRO",
    "event": "Croatia GCT 2019",
    "round": "11.1",
    "eco": "D85",
    "openingName": "Gruenfeld Defense:Exchange Variation:Modern Exchange Variation:"
  }
}