{
  "_id": "iJNZXj9PABA",
  "videoSnippet": {
    "schemaVersion": 1,
    "retrievedAt": "2023-02-12T19:40:50.184Z",
    "publishedAt": "2021-05-17T17:07:05Z",
    "title": "Wang Hao Retiring From Professional Chess || Enjoy This GEM",
    "description": "Read more about it here and watch the interview https://en.chessbase.com/post/wang-hao-declares-retirement-from-professional-chess\n\nYou are awesome! :)\nChannel: https://t.me/agadmatorChannel\nBar and the Library: https://t.me/BarAndTheLibrary\n\nWang Hao vs Hikaru Nakamura\nBiel Chess Festival (2012), Biel SUI, rd 3, Jul-25\nSicilian Defense: Najdorf. Polugayevsky Variation (B96)\n\n1. e4 c5 2. Nf3 d6 3. d4 cd4 4. Nd4 Nf6 5. Nc3 a6 6. Bg5 e6 7. f4 b5 8. e5 de5 9. fe5 Qc7 10. ef6 Qe5 11. Be2 Qg5 12. O-O Ra7 13. Qd3 Rd7 14. Ne4 Qe5 15. Nf3 Qc7 16. Qe3 Bb7 17. Nfg5 h6 18. Qh3 g6 19. Bd3 Nc6 20. Kh1 Ne5 21. Rae1 Bb4 22. Re3 Bd5 23. Be2 Nc4 24. Rd3 Qe5 25. a3 Ba5 26. Bg4 Nd6 27. Rd5 Qd5 28. Be6 fe6 29. f7 Kd8 30. Ne6 Kc8 31. f8Q Rf8 32. Rf8 Bd8 33. Nd6 Kb8 34. Rf1 Rd6 35. Nd8 Qc4 36. Rg1 Rd8 37. Qg3 Kb7 38. Qg6 Rd2 39. Qh6 Rc2 40. Qg7 Kb6 41. b4 Qd3 42. Re1 Qe3 43. Qf6 Kc7 44. Qf1 Rf2 45. Qg1 Qf4 46. h3 Qg3 47. Qh2\n\nCheck out agadmator's merch here https://teespring.com/stores/agadmators-swag-store\nhttps://teespring.com/design-with-a-story-tm\n\nMailbox where you can send stuff:\n\nAntonio Radić\nAGADMATOR d.o.o.\nFranje Tuđmana 12\nCroatia\n48260 Križevci \np.s. this is not my home address :)\n\nContact me: agadmatormanga@gmail.com or agadmator@gmail.com \n\nDownload agadmator chess clock for iOS here https://apps.apple.com/us/app/agadmator-chess-clock/id1474461379?ls=1&fbclid=IwAR2lhuxf60tpbW1vcvfXgdFzmShi6fHcrKxFF_NAhu9wLQwpJrAFbMWRYjk\n\nDownload agadmator chess clock for Android here https://play.google.com/store/Qapps/details?id=com.agadmator.chessclock&fbclid=IwAR3b_sRch6nsuW59-bWoirVDMMJ8V5jexZdUB0bsxQrc0Q8imvkBtqkHUXQ&rdid=com.agadmator.chessclock\n\nVideo created by OBS\n\n----------------------------------------------------------------------------------------------------------------------------------------\nIf you realllly enjoy my content, you're welcome to support me and my channel with a small donation via PayPal or Crypto.\n\nLink to PayPal donation https://www.paypal.me/agadmator\n\nMaiar Wallet @agadmator or join me here https://get.maiar.com/referral/pv0mam6l2a\nBTC address bc1qckd3ut0hqyymzv33eus97ld8klj02xhk2kcwld\nBCH address qzmfclyn69hqhjslls40r7r0dsttwe3tcsl946w4fr\nLTC address Laarf1RmvCpLt2BcSwC1PBLG3hRC4HjBrz\n\nNANO nano_1h1kgfaq88t1btwadqzx73rbha5hwbb88sxmfns851kwj8hnosdj51w388xx\nMonero 4AdvvqmC4xhPyyRSAEDxTTAoXdxAtX2Py6b8Eh4EQzBLGbgo5rY5Khcap1x76JrDJH87yibAE9b6TPwTsvBAiFFCLtM8Be7\nFor any other currency address, contact me via agadmator@gmail.com\n\nCheck out some of the books I enjoy https://www.amazon.com/ideas/amzn1.account.AFWWCIBWCL5PGEPL73FDWK632F7Q/2QAGBMLVXE7MG\n\nCheck out ALL my videos here https://www.youtube.com/watch?v=fYgd5ZLdHz8&list=PLDnx7w_xuguFTxcfiM11bB1JchtHclEJg\n\nFacebook: https://www.facebook.com/agadmatoryoutube\nTwitter: https://twitter.com/agadmator\nInstagram: https://www.instagram.com/agadmator/\nLichess: https://lichess.org/@/agadmator\nChess.com: agadmator\nLeague of Legends: agadmator (EUNE, my friend is using my EUWE account for a couple of years now)\nBlizzard: agadmator #2992 \nJoin our Discord Server here https://discord.gg/bY6BbRP",
    "thumbnail": {
      "default": {
        "url": "https://i.ytimg.com/vi/iJNZXj9PABA/default.jpg",
        "width": 120,
        "height": 90
      },
      "medium": {
        "url": "https://i.ytimg.com/vi/iJNZXj9PABA/mqdefault.jpg",
        "width": 320,
        "height": 180
      },
      "high": {
        "url": "https://i.ytimg.com/vi/iJNZXj9PABA/hqdefault.jpg",
        "width": 480,
        "height": 360
      },
      "standard": {
        "url": "https://i.ytimg.com/vi/iJNZXj9PABA/sddefault.jpg",
        "width": 640,
        "height": 480
      },
      "maxres": {
        "url": "https://i.ytimg.com/vi/iJNZXj9PABA/maxresdefault.jpg",
        "width": 1280,
        "height": 720
      }
    },
    "videoId": "iJNZXj9PABA"
  },
  "videoGame": [
    {
      "pgn": "1. e4 c5 2. Nf3 d6 3. d4 cxd4 4. Nxd4 Nf6 5. Nc3 a6 6. Bg5 e6 7. f4 b5 8. e5 dxe5 9. fxe5 Qc7 10. exf6 Qe5+ 11. Be2 Qxg5 12. O-O Ra7 13. Qd3 Rd7 14. Ne4 Qe5 15. Nf3 Qc7 16. Qe3 Bb7 17. Nfg5 h6 18. Qh3 g6 19. Bd3 Nc6 20. Kh1 Ne5 21. Rae1 Bb4 22. Re3 Bd5 23. Be2 Nc4 24. Rd3 Qe5 25. a3 Ba5 26. Bg4 Nd6 27. Rxd5 Qxd5 28. Bxe6 fxe6 29. f7+ Kd8 30. Nxe6+ Kc8 31. f8=Q+ Rxf8 32. Rxf8+ Bd8 33. Nxd6+ Kb8 34. Rf1 Rxd6 35. Nxd8 Qc4 36. Rg1 Rxd8 37. Qg3+ Kb7 38. Qxg6 Rd2 39. Qxh6 Rxc2 40. Qg7+ Kb6 41. b4 Qd3 42. Re1 Qe3 43. Qf6+ Kc7 44. Qf1 Rf2 45. Qg1 Qf4 46. h3 Qg3 47. Qh2  ",
      "fen": "8/2k5/p7/1p6/1P6/P5qP/5rPQ/4R2K b - - 0 1",
      "playerWhite": "Wang Hao",
      "playerBlack": "Hikaru Nakamura"
    }
  ],
  "chessCom": {
    "retrievedAt": "2023-02-12T16:04:08.978Z",
    "href": "https://www.chess.com/games/view/13251293",
    "playerWhite": "Wang Hao",
    "playerBlack": "Hikaru Nakamura",
    "result": "1-0",
    "movesCount": "47",
    "year": "2012"
  },
  "chesstempoCom": {
    "retrievedAt": "2023-02-12T16:49:49.298Z",
    "id": 3297993,
    "playerWhite": "Wang, Hao",
    "playerBlack": "Nakamura, Hikaru",
    "result": "w",
    "movesCount": 93,
    "date": "2012.7.25",
    "site": "Biel SUI",
    "event": "45th Biel GM",
    "round": "3",
    "eco": "B96",
    "openingName": "Sicilian Defense:Najdorf Variation:Polugayevsky  Variation:"
  },
  "videoContentDetails": {
    "duration": "PT17M13S"
  }
}