{
  "_id": "JzOG2HC2aIc",
  "videoSnippet": {
    "schemaVersion": 1,
    "retrievedAt": "2023-09-05T12:39:26.881Z",
    "publishedAt": "2023-09-05T11:42:38Z",
    "title": "Praggnanandhaa - \"The Joy of Wisdom\"",
    "description": "Download Mproov and Improve Your Chess Today! https://app.mproov.me/AgadYouTube1\n\nSearch all my videos easy https://agadmator-library.github.io/\n\nPhotos by Lennart Ootes\n\nRadjabov, Teimour (2686) - Praggnanandhaa (2645)\nTata Steel India Rapid (chess24.com) [1] 2023.09.05\nE11 Bogo-Indian defence\n\n1.d4 Nf6 2.c4 e6 3.Nf3 Bb4+ 4.Bd2 Qe7 5.g3 Bxd2+ 6.Qxd2 Nc6 7.Nc3 d5 8.Bg2 dxc4 9.O-O O-O 10.e4 Rb8 11.Rfe1 Rd8 12.Rad1 b5 13.a3 a5 14.Nd5 exd5 15.exd5 Qd6 16.dxc6 b4 17.Ne5 Be6 18.axb4 Qxb4 19.Qxb4 axb4 20.d5 Nxd5 21.Nxc4 Kf8 22.h3 Ra8 23.Ra1 b3 24.Ne5 Rxa1 25.Rxa1 Ke7 26.Ra7 Kd6 27.Nc4+ Kc5 28.Nd2 Nf6 29.Ne4+ Nxe4 30.Bxe4 Rd1+ 31.Kg2 Kd6 32.Ra8 Ke5 33.Kf3 Re1 34.Ra5+ Kd6 35.g4 h6 36.Rb5 Bc4 37.Rb4 Kc5 38.Rb7 Kd6 39.Rb4 Be6 40.Rd4+ Ke5 41.Rb4 g5 42.Rb5+ Kd4 43.Rb4+ Bc4 44.Ra4 Kc5 45.Ra7 Kd6 46.Ra4 Be2+ 47.Kg3 Bb5 48.Rd4+ Kc5 49.Rd5+ Kb6 50.Rd4 Rg1+ 51.Kf3 Rh1 52.Kg3 Rc1 53.Kf3 Bc4 54.Ke3 Kc5 55.Rd7 Re1+ 56.Kf3 Kb6 57.Rd4 Be6 58.Rb4+ Kc5 59.Rb7 Kd6 60.Rb4 Rh1 61.Rd4+ Ke5 62.Rd2 Re1\n\n00:00 Hello Everyone!\n\nThe Tata Steel Chess India Rapid tournament is a 10-player round-robin taking place September 5-7, 2023 in the National Library of India in Kolkata.\n\nPlayers receive 25 minutes for the entire game, plus a 10-second increment starting from move one. Official website: tatasteelchess.in\n\nCheck out agadmator's merch here https://teespring.com/stores/agadmators-swag-store\nhttps://teespring.com/design-with-a-story-tm\n\nMailbox where you can send stuff:\n\nAntonio Radić\nAGADMATOR d.o.o.\nFranje Tuđmana 12\nCroatia\n48260 Križevci \np.s. this is not my home address :)\n\nContact me: agadmator@gmail.com \n\nVideo created by OBS\n\n----------------------------------------------------------------------------------------------------------------------------------------\nIf you realllly enjoy my content, you're welcome to support me and my channel with a small donation via PayPal or Crypto.\n\nLink to PayPal donation https://www.paypal.me/agadmator\n\nMaiar Wallet @agadmator or join me here https://get.maiar.com/referral/pv0mam6l2a\nBTC address bc1qckd3ut0hqyymzv33eus97ld8klj02xhk2kcwld\nBCH address qzmfclyn69hqhjslls40r7r0dsttwe3tcsl946w4fr\nLTC address Laarf1RmvCpLt2BcSwC1PBLG3hRC4HjBrz\n\nNANO nano_1h1kgfaq88t1btwadqzx73rbha5hwbb88sxmfns851kwj8hnosdj51w388xx\nMonero 4AdvvqmC4xhPyyRSAEDxTTAoXdxAtX2Py6b8Eh4EQzBLGbgo5rY5Khcap1x76JrDJH87yibAE9b6TPwTsvBAiFFCLtM8Be7\nFor any other currency address, contact me via agadmator@gmail.com\n\nCheck out some of the books I enjoy https://www.amazon.com/ideas/amzn1.account.AFWWCIBWCL5PGEPL73FDWK632F7Q/2QAGBMLVXE7MG\n\nCheck out ALL my videos here https://www.youtube.com/watch?v=fYgd5ZLdHz8&list=PLDnx7w_xuguFTxcfiM11bB1JchtHclEJg\n\nFacebook: https://www.facebook.com/agadmatoryoutube\nTwitter: https://twitter.com/agadmator\nInstagram: https://www.instagram.com/agadmator/\nLichess: https://lichess.org/@/agadmator\nChess.com: agadmator\nLeague of Legends: agadmator (EUNE, my friend is using my EUWE account for a couple of years now)\n\n#youareawesome \"Watch me without ads on your Amazon devices (https://bit.ly/Agadmator_Amazon) and Roku TV (https://bit.ly/Agadmator_Roku)",
    "thumbnail": {
      "default": {
        "url": "https://i.ytimg.com/vi/JzOG2HC2aIc/default.jpg",
        "width": 120,
        "height": 90
      },
      "medium": {
        "url": "https://i.ytimg.com/vi/JzOG2HC2aIc/mqdefault.jpg",
        "width": 320,
        "height": 180
      },
      "high": {
        "url": "https://i.ytimg.com/vi/JzOG2HC2aIc/hqdefault.jpg",
        "width": 480,
        "height": 360
      },
      "standard": {
        "url": "https://i.ytimg.com/vi/JzOG2HC2aIc/sddefault.jpg",
        "width": 640,
        "height": 480
      },
      "maxres": {
        "url": "https://i.ytimg.com/vi/JzOG2HC2aIc/maxresdefault.jpg",
        "width": 1280,
        "height": 720
      }
    },
    "videoId": "JzOG2HC2aIc"
  },
  "videoContentDetails": {
    "duration": "PT11M55S"
  },
  "videoGame": [
    {
      "pgn": "1. d4 Nf6 2. c4 e6 3. Nf3 Bb4+ 4. Bd2 Qe7 5. g3 Bxd2+ 6. Qxd2 Nc6 7. Nc3 d5 8. Bg2 dxc4 9. O-O O-O 10. e4 Rb8 11. Rfe1 Rd8 12. Rad1 b5 13. a3 a5 14. Nd5 exd5 15. exd5 Qd6 16. dxc6 b4 17. Ne5 Be6 18. axb4 Qxb4 19. Qxb4 axb4 20. d5 Nxd5 21. Nxc4 Kf8 22. h3 Ra8 23. Ra1 b3 24. Ne5 Rxa1 25. Rxa1 Ke7 26. Ra7 Kd6 27. Nc4+ Kc5 28. Nd2 Nf6 29. Ne4+ Nxe4 30. Bxe4 Rd1+ 31. Kg2 Kd6 32. Ra8 Ke5 33. Kf3 Re1 34. Ra5+ Kd6 35. g4 h6 36. Rb5 Bc4 37. Rb4 Kc5 38. Rb7 Kd6 39. Rb4 Be6 40. Rd4+ Ke5 41. Rb4 g5 42. Rb5+ Kd4 43. Rb4+ Bc4 44. Ra4 Kc5 45. Ra7 Kd6 46. Ra4 Be2+ 47. Kg3 Bb5 48. Rd4+ Kc5 49. Rd5+ Kb6 50. Rd4 Rg1+ 51. Kf3 Rh1 52. Kg3 Rc1 53. Kf3 Bc4 54. Ke3 Kc5 55. Rd7 Re1+ 56. Kf3 Kb6 57. Rd4 Be6 58. Rb4+ Kc5 59. Rb7 Kd6 60. Rb4 Rh1 61. Rd4+ Ke5 62. Rd2 Re1",
      "fen": "8/2p2p2/2P1b2p/4k1p1/4B1P1/1p3K1P/1P1R1P2/4r3 w - - 0 1",
      "playerWhite": "Teimour Radjabov",
      "playerBlack": "Praggnanandhaa R",
      "date": "2023-09-05"
    }
  ],
  "chessCom": {
    "retrievedAt": "2023-09-05T12:39:27.331Z",
    "playerWhite": "Teimour Radjabov",
    "playerBlack": "Praggnanandhaa Rameshbabu",
    "href": "https://www.chess.com/games/view/16641695",
    "result": "0-1",
    "movesCount": 62,
    "year": 2023
  },
  "chess365": {
    "retrievedAt": "2024-01-18T09:44:39.627Z",
    "playerWhite": "Teimour Radjabov",
    "playerBlack": "Praggnanandhaa R",
    "href": "https://www.365chess.com/game.php?gid=4434282",
    "result": "0-1",
    "movesCount": 62,
    "year": 2023,
    "eco": "E11",
    "tournament": "Tata Steel IND Rapid Open"
  },
  "lichessMasters": {
    "reason": "NOT_FOUND",
    "retrievedAt": "2023-09-05T12:39:38.750Z"
  },
  "stockfishEval": [
    {
      "cp": -707,
      "mate": null
    }
  ],
  "chesstempoCom": {
    "retrievedAt": "2023-11-18T09:45:46.381Z",
    "playerWhite": "Radjabov, Teimour",
    "playerBlack": "Praggnanandhaa R, ",
    "id": 5722601,
    "result": "b",
    "movesCount": 124,
    "date": "2023.9.5",
    "site": "Kolkata IND",
    "event": "Tata Steel IND Rapid Open",
    "round": "1.5",
    "eco": "E11",
    "openingName": "Bogo-Indian Defense:Nimzowitsch Variation::"
  },
  "lichessGameId": [
    {
      "id": "k68PA0qC"
    }
  ]
}