{
  "_id": "MKBKxZK_H2M",
  "videoSnippet": {
    "schemaVersion": 1,
    "retrievedAt": "2023-06-26T17:26:11.411Z",
    "publishedAt": "2023-06-26T17:22:45Z",
    "title": "I'll Just Grind, If You Don't Mind",
    "description": "Join our Telegram channel here t.me/agadmatorChannel (https://t.me/agadmatorChannel)\nJoin our Telegram group here t.me/BarAndTheLibrary (https://t.me/BarAndTheLibrary)\nSearch all my videos easy https://agadmator-library.github.io/\n\nNepomniachtchi, Ian (2760) - Carlsen, Magnus (2829)\nGlobal Chess League (chess24.com) [6] 2023.06.26\nB22 Sicilian, Alapin's variation (2.c3)\n\n1.e4 c5 2.c3 e5 3.Nf3 Nc6 4.Bc4 Nf6 5.Ng5 d5 6.exd5 Nxd5 7.d4 cxd4 8.Qb3 Be6 9.Nxe6 fxe6 10.Qxb7 Rc8 11.O-O Qd7 12.Qb5 Be7 13.Bb3 O-O 14.Qd3 Na5 15.Bd1 Rfd8 16.Bf3 dxc3 17.Nxc3 Nxc3 18.Qxd7 Rxd7 19.bxc3 Rxc3 20.Bb2 Rc5 21.Rad1 Rxd1 22.Rxd1 Nc4 23.Bc3 e4 24.Bd4 Ra5 25.Bxe4 Rxa2 26.g3 Nd2 27.Bc6 a5 28.Kg2 Kf7 29.Bc3 Nc4 30.Rd7 Ne3+ 31.Kf3 Ra3 32.Bb2 Rb3 33.fxe3 Rxb2 34.Ra7 Rxh2 35.Rxa5 h5 36.Ra6 Bd6 37.Bb5 Ke7 38.Bc4 g5 39.e4 Rc2 40.Ba2 Rc5 41.Ke3 h4 42.gxh4 gxh4 43.Ra7+ Kf6 44.Rh7 h3 45.Kd4 Rc2 46.Bxe6 Be5+ 47.Kd5 Rd2+ 48.Kc6 h2 49.Bg4 Rf2 50.Rh3 Kg5 51.Bf3 Rxf3 52.Rxf3 h1=Q 53.Rf5+ Kg4 54.Rxe5 Kf4 55.Re6 Qd1 56.Kc7 Qd4 57.Re7 Ke3 58.Re6 Qg7+ 59.Kd6 Qf8+ 60.Kd5 Qa8+ 61.Kc5 Qd8 62.Kc6 Qa5 63.Kd6 Kd4 64.Ke7 Qc7+ 65.Kf6 Qf4+ 66.Ke7 Kc5 67.Kd7 Qf7+ 68.Re7 Qf6 69.Re6 Qd4+ 70.Ke7 Qg7+ 71.Ke8 Qh7 72.Re7 Qg6+ 73.Kf8 Kc6 74.e5 Kd5 75.e6 Ke5 76.Rg7 Qf6+ 77.Rf7 Qd8+ 78.Kg7 Kxe6 79.Rf1 Qg5+ 80.Kf8 Qb5 81.Rf7 Qh5 82.Re7+ Kf6\n\n00:00 Hello Everyone!\n\nThe Global Chess League is a 6-team double round-robin tournament taking place from June 22 to July 1, 2023 in Dubai, UAE.\n\nPlayers receive 15 minutes for the entire game, plus a 10-second increment starting from move one. Wins with Black are worth 4 board points, wins with White 3, a draw 1. Official website: globalchessleague.com\n\nCheck out agadmator's merch here https://teespring.com/stores/agadmators-swag-store\nhttps://teespring.com/design-with-a-story-tm\n\nMailbox where you can send stuff:\n\nAntonio Radić\nAGADMATOR d.o.o.\nFranje Tuđmana 12\nCroatia\n48260 Križevci \np.s. this is not my home address :)\n\nContact me: agadmator@gmail.com \n\nVideo created by OBS\n\n----------------------------------------------------------------------------------------------------------------------------------------\nIf you realllly enjoy my content, you're welcome to support me and my channel with a small donation via PayPal or Crypto.\n\nLink to PayPal donation https://www.paypal.me/agadmator\n\nMaiar Wallet @agadmator or join me here https://get.maiar.com/referral/pv0mam6l2a\nBTC address bc1qckd3ut0hqyymzv33eus97ld8klj02xhk2kcwld\nBCH address qzmfclyn69hqhjslls40r7r0dsttwe3tcsl946w4fr\nLTC address Laarf1RmvCpLt2BcSwC1PBLG3hRC4HjBrz\n\nNANO nano_1h1kgfaq88t1btwadqzx73rbha5hwbb88sxmfns851kwj8hnosdj51w388xx\nMonero 4AdvvqmC4xhPyyRSAEDxTTAoXdxAtX2Py6b8Eh4EQzBLGbgo5rY5Khcap1x76JrDJH87yibAE9b6TPwTsvBAiFFCLtM8Be7\nFor any other currency address, contact me via agadmator@gmail.com\n\nCheck out some of the books I enjoy https://www.amazon.com/ideas/amzn1.account.AFWWCIBWCL5PGEPL73FDWK632F7Q/2QAGBMLVXE7MG\n\nCheck out ALL my videos here https://www.youtube.com/watch?v=fYgd5ZLdHz8&list=PLDnx7w_xuguFTxcfiM11bB1JchtHclEJg\n\nFacebook: https://www.facebook.com/agadmatoryoutube\nTwitter: https://twitter.com/agadmator\nInstagram: https://www.instagram.com/agadmator/\nLichess: https://lichess.org/@/agadmator\nChess.com: agadmator\nLeague of Legends: agadmator (EUNE, my friend is using my EUWE account for a couple of years now)\nBlizzard: agadmator #2992 \nJoin our Discord Server here https://discord.gg/bY6BbRP\n\n#youareawesome",
    "thumbnail": {
      "default": {
        "url": "https://i.ytimg.com/vi/MKBKxZK_H2M/default.jpg",
        "width": 120,
        "height": 90
      },
      "medium": {
        "url": "https://i.ytimg.com/vi/MKBKxZK_H2M/mqdefault.jpg",
        "width": 320,
        "height": 180
      },
      "high": {
        "url": "https://i.ytimg.com/vi/MKBKxZK_H2M/hqdefault.jpg",
        "width": 480,
        "height": 360
      },
      "standard": {
        "url": "https://i.ytimg.com/vi/MKBKxZK_H2M/sddefault.jpg",
        "width": 640,
        "height": 480
      },
      "maxres": {
        "url": "https://i.ytimg.com/vi/MKBKxZK_H2M/maxresdefault.jpg",
        "width": 1280,
        "height": 720
      }
    },
    "videoId": "MKBKxZK_H2M"
  },
  "videoContentDetails": {
    "duration": "PT15M54S"
  },
  "videoGame": [
    {
      "pgn": "1. e4 c5 2. c3 e5 3. Nf3 Nc6 4. Bc4 Nf6 5. Ng5 d5 6. exd5 Nxd5 7. d4 cxd4 8. Qb3 Be6 9. Nxe6 fxe6 10. Qxb7 Rc8 11. O-O Qd7 12. Qb5 Be7 13. Bb3 O-O 14. Qd3 Na5 15. Bd1 Rfd8 16. Bf3 dxc3 17. Nxc3 Nxc3 18. Qxd7 Rxd7 19. bxc3 Rxc3 20. Bb2 Rc5 21. Rad1 Rxd1 22. Rxd1 Nc4 23. Bc3 e4 24. Bd4 Ra5 25. Bxe4 Rxa2 26. g3 Nd2 27. Bc6 a5 28. Kg2 Kf7 29. Bc3 Nc4 30. Rd7 Ne3+ 31. Kf3 Ra3 32. Bb2 Rb3 33. fxe3 Rxb2 34. Ra7 Rxh2 35. Rxa5 h5 36. Ra6 Bd6 37. Bb5 Ke7 38. Bc4 g5 39. e4 Rc2 40. Ba2 Rc5 41. Ke3 h4 42. gxh4 gxh4 43. Ra7+ Kf6 44. Rh7 h3 45. Kd4 Rc2 46. Bxe6 Be5+ 47. Kd5 Rd2+ 48. Kc6 h2 49. Bg4 Rf2 50. Rh3 Kg5 51. Bf3 Rxf3 52. Rxf3 h1=Q 53. Rf5+ Kg4 54. Rxe5 Kf4 55. Re6 Qd1 56. Kc7 Qd4 57. Re7 Ke3 58. Re6 Qg7+ 59. Kd6 Qf8+ 60. Kd5 Qa8+ 61. Kc5 Qd8 62. Kc6 Qa5 63. Kd6 Kd4 64. Ke7 Qc7+ 65. Kf6 Qf4+ 66. Ke7 Kc5 67. Kd7 Qf7+ 68. Re7 Qf6 69. Re6 Qd4+ 70. Ke7 Qg7+ 71. Ke8 Qh7 72. Re7 Qg6+ 73. Kf8 Kc6 74. e5 Kd5 75. e6 Ke5 76. Rg7 Qf6+ 77. Rf7 Qd8+ 78. Kg7 Kxe6 79. Rf1 Qg5+ 80. Kf8 Qb5 81. Rf7 Qh5 82. Re7+ Kf6",
      "fen": "5K2/4R3/5k2/7q/8/8/8/8 w - - 0 1",
      "playerWhite": "Ian Nepomniachtchi",
      "playerBlack": "Magnus Carlsen",
      "date": "2023-06-26"
    }
  ],
  "chessCom": {
    "reason": "NOT_FOUND",
    "retrievedAt": "2023-06-26T17:26:11.879Z"
  },
  "chesstempoCom": {
    "reason": "NOT_FOUND",
    "retrievedAt": "2023-06-26T17:26:12.347Z"
  },
  "chess365": {
    "reason": "NOT_FOUND",
    "retrievedAt": "2023-07-02T09:44:53.781Z"
  },
  "lichessMasters": {
    "reason": "NOT_FOUND",
    "retrievedAt": "2023-06-26T17:26:13.174Z"
  },
  "stockfishEval": [
    {
      "cp": null,
      "mate": -4
    }
  ]
}