{
  "_id": "o5ZxthpSK4k",
  "videoSnippet": {
    "schemaVersion": 1,
    "retrievedAt": "2025-03-11T15:30:51.894Z",
    "publishedAt": "2025-03-11T15:01:08Z",
    "title": "Fischer Goes Engine Mode! || Ivkov vs Fischer || Second Piatigorsky Cup (1966)",
    "description": "https://www.youtube.com/watch?v=DcxzFtNBQwI\nhttps://www.youtube.com/watch?v=gsvITjkjYv4\nSearch all my videos easy https://agadmator-library.github.io/\n\n0:00 Hello Everyone!\n01:40 Game Starts!\n02:59 Completely New Game!\n15:45 Legends Of The Channel!\n\nBorislav Ivkov vs Robert James Fischer\nSecond Piatigorsky Cup (1966), Santa Monica, CA USA, rd 3, Jul-20\nIndian Game: King's Indian. Fianchetto Variation (A49)\n\n1. d4 Nf6 2. Nf3 g6 3. g3 Bg7 4. Bg2 O-O 5. O-O d6 6. Nc3 d5 7. Ne5 c6 8. e4 Be6 9. ed5 cd5 10. Ne2 Nc6 11. Nf4 Bf5 12. c3 Be4 13. Bh3 Qc7 14. Nfd3 Bd3 15. Nd3 e6 16. Bf4 Qd8 17. Re1 Re8 18. Bg2 Nd7 19. h4 h5 20. Bf3 b5 21. a3 a5 22. Qe2 Rc8 23. Bd6 Qb6 24. Be5 Nde5 25. Ne5 Ne5 26. de5 b4 27. ab4 ab4 28. Qe3 Qe3 29. Re3 bc3 30. bc3 Rc5 31. Be2 Rec8 32. Ra3 Bf8 33. Rb3 Be7 34. Kg2 Bd8 35. Ba6 Ra8 36. Rf3 Bc7 37. Rb5 Rc4 38. Bb7 Ra3 39. Re3 Kg7 40. Bc8 Rac3 41. Re1 Rc2 42. Bd\n\nCheck out agadmator's merch here https://teespring.com/stores/agadmators-swag-store\nhttps://teespring.com/design-with-a-story-tm\n\nMailbox where you can send stuff:\n\nAntonio Radić\nAGADMATOR d.o.o.\nFranje Tuđmana 12\nCroatia\n48260 Križevci \np.s. this is not my home address :)\n\nContact me: agadmator@gmail.com \n\nVideo created by OBS\n\n----------------------------------------------------------------------------------------------------------------------------------------\nIf you realllly enjoy my content, you're welcome to support me and my channel with a small donation via PayPal or Crypto.\n\nLink to PayPal donation https://www.paypal.me/agadmator\n\nMaiar Wallet @agadmator or join me here https://get.maiar.com/referral/pv0mam6l2a\nBTC address bc1qckd3ut0hqyymzv33eus97ld8klj02xhk2kcwld\nBCH address qzmfclyn69hqhjslls40r7r0dsttwe3tcsl946w4fr\nLTC address Laarf1RmvCpLt2BcSwC1PBLG3hRC4HjBrz\nNANO nano_1h1kgfaq88t1btwadqzx73rbha5hwbb88sxmfns851kwj8hnosdj51w388xx\nMonero 4AdvvqmC4xhPyyRSAEDxTTAoXdxAtX2Py6b8Eh4EQzBLGbgo5rY5Khcap1x76JrDJH87yibAE9b6TPwTsvBAiFFCLtM8Be7\nFor any other currency address, contact me via agadmator@gmail.com\n\nCheck out some of the books I enjoy https://www.amazon.com/ideas/amzn1.account.AFWWCIBWCL5PGEPL73FDWK632F7Q/2QAGBMLVXE7MG\n\nCheck out ALL my videos here https://www.youtube.com/watch?v=fYgd5ZLdHz8&list=PLDnx7w_xuguFTxcfiM11bB1JchtHclEJg\n\nFacebook: https://www.facebook.com/agadmatoryoutube\nTwitter: https://twitter.com/agadmator\nInstagram: https://www.instagram.com/agadmator/\nLichess: https://lichess.org/@/agadmator\nChess.com: agadmator\nLeague of Legends: agadmator (EUNE, my friend is using my EUWE account for a couple of years now)\nBlizzard: agadmator #2992 \nJoin our Discord Server here https://discord.gg/bY6BbRP\n\n#youareawesome \"Watch me without ads on your Amazon devices (https://bit.ly/Agadmator_Amazon) and Roku TV (https://bit.ly/Agadmator_Roku)",
    "thumbnail": {
      "default": {
        "url": "https://i.ytimg.com/vi/o5ZxthpSK4k/default.jpg",
        "width": 120,
        "height": 90
      },
      "medium": {
        "url": "https://i.ytimg.com/vi/o5ZxthpSK4k/mqdefault.jpg",
        "width": 320,
        "height": 180
      },
      "high": {
        "url": "https://i.ytimg.com/vi/o5ZxthpSK4k/hqdefault.jpg",
        "width": 480,
        "height": 360
      },
      "standard": {
        "url": "https://i.ytimg.com/vi/o5ZxthpSK4k/sddefault.jpg",
        "width": 640,
        "height": 480
      },
      "maxres": {
        "url": "https://i.ytimg.com/vi/o5ZxthpSK4k/maxresdefault.jpg",
        "width": 1280,
        "height": 720
      }
    },
    "videoId": "o5ZxthpSK4k"
  },
  "videoContentDetails": {
    "duration": "PT16M9S"
  },
  "videoGame": [
    {
      "playerWhite": "Borislav Ivkov",
      "playerBlack": "Robert James Fischer",
      "date": "1966-07-20"
    }
  ],
  "lichessGameId": [
    {}
  ],
  "stockfishEval": [
    null
  ]
}