{
  "_id": "wM1P_KBpJLs",
  "videoSnippet": {
    "schemaVersion": 1,
    "retrievedAt": "2023-02-12T19:40:59.514Z",
    "publishedAt": "2018-10-23T18:04:07Z",
    "title": "Who Needs a Queen? | Praggu vs Eljanov | Isle of Man (2018)",
    "description": "Follow me on Instagram for extra content: https://www.instagram.com/agadmator/\n\nRameshbabu Praggnanandhaa vs Pavel Eljanov\nIsle of Man Open Tournament, Round 3\n23 Oct 2018.\nSicilian Defense: Open: Classical, Richter Rauser Variation (B62)\n\n1. e4 c5 2. Nf3 Nc6 3. d4 cxd4 4. Nxd4 Nf6 5. Nc3 d6 6. Bg5 e6 7. Qd2 a6 8. O-O-O Be7 9. f3 Qc7 10. h4 Nxd4 11. Qxd4 b5 12. Qd2 Bb7 13. Kb1 O-O 14. Ne2 Rac8 15. Nd4 Rfe8 16. g4 Nd7 17. Bxe7 Rxe7 18. h5 d5 19. h6 g6 20. exd5 Bxd5 21. Bd3 Qe5 22. Be4 Bxe4 23. fxe4 Nf6 24. Rhe1 Rd7 25. g5 Ng4 26. Qg2 Qxg5 27. e5 Qf4 28. Nc6 Ne3 29. Rxd7 Nxg2 30. Ne7+ Kf8 31. Nxc8 Qxh6 32. Rf1 Nf4 33. Nd6 g5 34. Nxf7 Qg7 35. Rd8+ Ke7 36. Ra8 Qxf7 37. Ra7+ Kf8 38. Rxf7+ Kxf7 39. b3 h5 40. c4 bxc4 41. bxc4 h4 42. c5 Ke7 43. Rd1 h3 44. c6 Nd5 45. Rg1 h2 46. Rh1 Nb4 47. c7 Kd7 48. Rxh2 Kxc7 49. Rh6 Kd7 50. Rg6 a5 51. Rxg5 Kc6 52. Kb2 Kd5 53. Kb3 Kd4 54. Rh5 Nc6 55. Ka4 Kc4 56. Rh6 Kd5 57. Kb5 Nxe5 58. Rh5 Kd4 59. Kxa5 Nd3 60. Kb5 e5 61. a4 Nf4 62. Rh4 Kd5 63. a5 Ne6 64. Rc4\n\nOfficial page https://iominternationalchess.com\nFollow iomchess https://twitter.com/iomchess\n\nCheck out the score between any player here http://www.chessgames.com\n\n----------------------------------------------------------------------------------------------------------------------------------------------------------------------------------\nIf you realllly enjoy my content, you're welcome to support me and my channel with a small donation via PayPal or Crypto.\n\nLink to PayPal donation https://www.paypal.me/agadmator\n\nMaiar Wallet @agadmator or https://get.maiar.com/referral/pv0mam6l2a\nBTC address bc1qckd3ut0hqyymzv33eus97ld8klj02xhk2kcwld\nBCH address qzmfclyn69hqhjslls40r7r0dsttwe3tcsl946w4fr\nLTC address Laarf1RmvCpLt2BcSwC1PBLG3hRC4HjBrz\n\nNANO nano_1h1kgfaq88t1btwadqzx73rbha5hwbb88sxmfns851kwj8hnosdj51w388xx\nMonero 4AdvvqmC4xhPyyRSAEDxTTAoXdxAtX2Py6b8Eh4EQzBLGbgo5rY5Khcap1x76JrDJH87yibAE9b6TPwTsvBAiFFCLtM8Be7\nFor any other currency address, contact me via agadmator@gmail.com\n\nCheck out some of the books I enjoy https://www.amazon.com/ideas/amzn1.account.AFWWCIBWCL5PGEPL73FDWK632F7Q/2QAGBMLVXE7MG\n\nCheck out ALL my videos here https://www.youtube.com/watch?v=fYgd5ZLdHz8&list=PLDnx7w_xuguFTxcfiM11bB1JchtHclEJg\n\nSteemit: https://steemit.com/@agadmator/\nFacebook: https://www.facebook.com/agadmatoryoutube\nTwitter: https://twitter.com/agadmator\nInstagram: https://www.instagram.com/agadmator/\nLichess: https://lichess.org/@/agadmator\nChess.com: agadmator\nLeague of Legends: agadmator (EUNE, my friend is using my EUWE account for a couple of years now)\nBlizzard: agadmator #2992 \nCheck out my Hearthstone channel here https://www.youtube.com/channel/UCDKefsd8PMI0FXHwPi5yscg\n\nCheck out the SUBSCRIBERS VIDEO https://www.youtube.com/watch?v=p-xa0SkpIiA\n\nSend your photos and videos here:\nsubscribers.videos.agadmator@gmail.com\n\n\n#iomchess",
    "thumbnail": {
      "default": {
        "url": "https://i.ytimg.com/vi/wM1P_KBpJLs/default.jpg",
        "width": 120,
        "height": 90
      },
      "medium": {
        "url": "https://i.ytimg.com/vi/wM1P_KBpJLs/mqdefault.jpg",
        "width": 320,
        "height": 180
      },
      "high": {
        "url": "https://i.ytimg.com/vi/wM1P_KBpJLs/hqdefault.jpg",
        "width": 480,
        "height": 360
      },
      "standard": {
        "url": "https://i.ytimg.com/vi/wM1P_KBpJLs/sddefault.jpg",
        "width": 640,
        "height": 480
      },
      "maxres": {
        "url": "https://i.ytimg.com/vi/wM1P_KBpJLs/maxresdefault.jpg",
        "width": 1280,
        "height": 720
      }
    },
    "videoId": "wM1P_KBpJLs"
  },
  "videoGame": [
    {
      "pgn": "1. e4 c5 2. Nf3 Nc6 3. d4 cxd4 4. Nxd4 Nf6 5. Nc3 d6 6. Bg5 e6 7. Qd2 a6 8. O-O-O Be7 9. f3 Qc7 10. h4 Nxd4 11. Qxd4 b5 12. Qd2 Bb7 13. Kb1 O-O 14. Ne2 Rac8 15. Nd4 Rfe8 16. g4 Nd7 17. Bxe7 Rxe7 18. h5 d5 19. h6 g6 20. exd5 Bxd5 21. Bd3 Qe5 22. Be4 Bxe4 23. fxe4 Nf6 24. Rhe1 Rd7 25. g5 Ng4 26. Qg2 Qxg5 27. e5 Qf4 28. Nc6 Ne3 29. Rxd7 Nxg2 30. Ne7+ Kf8 31. Nxc8 Qxh6 32. Rf1 Nf4 33. Nd6 g5 34. Nxf7 Qg7 35. Rd8+ Ke7 36. Ra8 Qxf7 37. Ra7+ Kf8 38. Rxf7+ Kxf7 39. b3 h5 40. c4 bxc4 41. bxc4 h4 42. c5 Ke7 43. Rd1 h3 44. c6 Nd5 45. Rg1 h2 46. Rh1 Nb4 47. c7 Kd7 48. Rxh2 Kxc7 49. Rh6 Kd7 50. Rg6 a5 51. Rxg5 Kc6 52. Kb2 Kd5 53. Kb3 Kd4 54. Rh5 Nc6 55. Ka4 Kc4 56. Rh6 Kd5 57. Kb5 Nxe5 58. Rh5 Kd4 59. Kxa5 Nd3 60. Kb5 e5 61. a4 Nf4 62. Rh4 Kd5 63. a5 Ne6 64. Rc4",
      "fen": "8/8/4n3/PK1kp3/2R5/8/8/8 b - - 0 1",
      "playerWhite": "Praggnanandhaa R",
      "playerBlack": "Pavel Eljanov"
    }
  ],
  "chessCom": {
    "retrievedAt": "2023-02-12T18:31:54.257Z",
    "href": "https://www.chess.com/games/view/15095967",
    "playerWhite": "Praggnanandhaa R",
    "playerBlack": "Pavel Eljanov",
    "result": "1-0",
    "movesCount": "64",
    "year": "2018"
  },
  "chesstempoCom": {
    "retrievedAt": "2023-02-12T17:55:46.040Z",
    "id": 4418111,
    "playerWhite": "Praggnanandhaa R, ",
    "playerBlack": "Eljanov, Pavel",
    "result": "w",
    "movesCount": 127,
    "date": "2018.10.22",
    "site": "Douglas ENG",
    "event": "chess.com IoM Masters",
    "round": "3.20",
    "eco": "B62",
    "openingName": "Sicilian Defense:Richter-Rauzer Variation:Neo-Modern Variation:Early deviations"
  },
  "chess365": {
    "retrievedAt": "2023-02-22T13:29:59.827Z",
    "href": "https://www.365chess.com/game.php?gid=4150178",
    "playerWhite": "Praggnanandhaa R",
    "playerBlack": "Pavel Eljanov",
    "result": "1-0",
    "movesCount": 64,
    "year": 2018,
    "eco": "B66",
    "tournament": "IoM Masters"
  },
  "videoContentDetails": {
    "duration": "PT20M48S"
  },
  "stockfishEval": [
    {
      "cp": -4847,
      "mate": null
    }
  ],
  "lichessMasters": {
    "reason": "NOT_FOUND",
    "retrievedAt": "2023-10-14T09:20:44.900Z"
  },
  "lichessGameId": [
    {
      "id": "C04tX0sS"
    }
  ],
  "lichessGameEval": [
    {
      "id": "C04tX0sS",
      "rated": false,
      "variant": "standard",
      "speed": "correspondence",
      "perf": "correspondence",
      "createdAt": 1540319717203,
      "lastMoveAt": 1540319717203,
      "status": "started",
      "source": "import",
      "players": {
        "white": {
          "name": "?",
          "analysis": {
            "inaccuracy": 6,
            "mistake": 0,
            "blunder": 0,
            "acpl": 22,
            "accuracy": 93
          }
        },
        "black": {
          "name": "?",
          "analysis": {
            "inaccuracy": 10,
            "mistake": 2,
            "blunder": 1,
            "acpl": 39,
            "accuracy": 89
          }
        }
      },
      "opening": {
        "eco": "B66",
        "name": "Sicilian Defense: Richter-Rauzer Variation, Neo-Modern Variation, Early Deviations",
        "ply": 14
      },
      "moves": "e4 c5 Nf3 Nc6 d4 cxd4 Nxd4 Nf6 Nc3 d6 Bg5 e6 Qd2 a6 O-O-O Be7 f3 Qc7 h4 Nxd4 Qxd4 b5 Qd2 Bb7 Kb1 O-O Ne2 Rac8 Nd4 Rfe8 g4 Nd7 Bxe7 Rxe7 h5 d5 h6 g6 exd5 Bxd5 Bd3 Qe5 Be4 Bxe4 fxe4 Nf6 Rhe1 Rd7 g5 Ng4 Qg2 Qxg5 e5 Qf4 Nc6 Ne3 Rxd7 Nxg2 Ne7+ Kf8 Nxc8 Qxh6 Rf1 Nf4 Nd6 g5 Nxf7 Qg7 Rd8+ Ke7 Ra8 Qxf7 Ra7+ Kf8 Rxf7+ Kxf7 b3 h5 c4 bxc4 bxc4 h4 c5 Ke7 Rd1 h3 c6 Nd5 Rg1 h2 Rh1 Nb4 c7 Kd7 Rxh2 Kxc7 Rh6 Kd7 Rg6 a5 Rxg5 Kc6 Kb2 Kd5 Kb3 Kd4 Rh5 Nc6 Ka4 Kc4 Rh6 Kd5 Kb5 Nxe5 Rh5 Kd4 Kxa5 Nd3 Kb5 e5 a4 Nf4 Rh4 Kd5 a5 Ne6 Rc4",
      "pgn": "[Event \"Import\"]\n[Site \"https://lichess.org/C04tX0sS\"]\n[Date \"2018.10.23\"]\n[White \"?\"]\n[Black \"?\"]\n[Result \"*\"]\n[UTCDate \"2018.10.23\"]\n[UTCTime \"18:35:17\"]\n[WhiteElo \"?\"]\n[BlackElo \"?\"]\n[Variant \"Standard\"]\n[TimeControl \"-\"]\n[ECO \"B66\"]\n[Opening \"Sicilian Defense: Richter-Rauzer Variation, Neo-Modern Variation, Early Deviations\"]\n[Termination \"Unterminated\"]\n\n1. e4 { [%eval 0.12] } 1... c5 { [%eval 0.18] } 2. Nf3 { [%eval 0.15] } 2... Nc6 { [%eval 0.08] } 3. d4 { [%eval 0.15] } 3... cxd4 { [%eval 0.0] } 4. Nxd4 { [%eval 0.08] } 4... Nf6 { [%eval 0.47] } 5. Nc3 { [%eval 0.17] } 5... d6 { [%eval 0.57] } 6. Bg5 { [%eval 0.26] } 6... e6 { [%eval 0.35] } 7. Qd2 { [%eval 0.23] } 7... a6 { [%eval 0.26] } 8. O-O-O { [%eval 0.5] } 8... Be7 { [%eval 0.82] } 9. f3 { [%eval 0.17] } 9... Qc7 { [%eval 0.53] } 10. h4 { [%eval 0.08] } 10... Nxd4 { [%eval 0.15] } 11. Qxd4 { [%eval 0.12] } 11... b5 { [%eval 0.31] } 12. Qd2 { [%eval 0.08] } 12... Bb7 { [%eval 0.15] } 13. Kb1 { [%eval 0.0] } 13... O-O { [%eval 0.28] } 14. Ne2 { [%eval -0.47] } 14... Rac8 { [%eval 0.1] } 15. Nd4 { [%eval -0.19] } 15... Rfe8 { [%eval -0.12] } 16. g4 { [%eval -0.1] } 16... Nd7 { [%eval 0.0] } 17. Bxe7 { [%eval 0.0] } 17... Rxe7 { [%eval -0.11] } 18. h5 { [%eval -0.21] } 18... d5 { [%eval -0.09] } 19. h6 { [%eval -0.36] } 19... g6 { [%eval -0.17] } 20. exd5 { [%eval -0.39] } 20... Bxd5 { [%eval -0.15] } 21. Bd3 { [%eval -0.27] } 21... Qe5 { [%eval 0.35] } 22. Be4 { [%eval -0.6] } 22... Bxe4 { [%eval -0.4] } 23. fxe4 { [%eval -0.43] } 23... Nf6 { [%eval -0.42] } 24. Rhe1 { [%eval -0.5] } 24... Rd7 { [%eval -0.09] } 25. g5 { [%eval -0.21] } 25... Ng4 { [%eval -0.3] } 26. Qg2 { [%eval -0.43] } 26... Qxg5 { [%eval -0.45] } 27. e5 { [%eval -0.47] } 27... Qf4 { [%eval -0.32] } 28. Nc6 { [%eval -1.31] } 28... Ne3 { [%eval 0.0] } 29. Rxd7 { [%eval 0.0] } 29... Nxg2 { [%eval 0.0] } 30. Ne7+ { [%eval 0.0] } 30... Kf8 { [%eval 0.0] } 31. Nxc8 { [%eval 0.0] } 31... Qxh6 { [%eval 0.0] } 32. Rf1 { [%eval 0.0] } 32... Nf4 { [%eval 0.0] } 33. Nd6 { [%eval 0.0] } 33... g5 { [%eval 0.0] } 34. Nxf7 { [%eval -1.07] } 34... Qg7 { [%eval 0.0] } 35. Rd8+ { [%eval -0.6] } 35... Ke7 { [%eval -0.44] } 36. Ra8 { [%eval -0.42] } 36... Qxf7 { [%eval 0.0] } 37. Ra7+ { [%eval 0.0] } 37... Kf8 { [%eval 0.0] } 38. Rxf7+ { [%eval 0.0] } 38... Kxf7 { [%eval 0.0] } 39. b3 { [%eval 0.0] } 39... h5 { [%eval 0.83] } 40. c4 { [%eval 0.54] } 40... bxc4 { [%eval 0.62] } 41. bxc4 { [%eval 0.55] } 41... h4 { [%eval 1.25] } 42. c5 { [%eval 0.78] } 42... Ke7 { [%eval 1.6] } 43. Rd1 { [%eval 1.57] } 43... h3 { [%eval 2.02] } 44. c6 { [%eval 1.95] } 44... Nd5 { [%eval 1.94] } 45. Rg1 { [%eval 1.94] } 45... h2 { [%eval 2.16] } 46. Rh1 { [%eval 2.11] } 46... Nb4 { [%eval 2.15] } 47. c7 { [%eval 2.15] } 47... Kd7 { [%eval 2.15] } 48. Rxh2 { [%eval 2.15] } 48... Kxc7 { [%eval 2.14] } 49. Rh6 { [%eval 2.07] } 49... Kd7 { [%eval 2.14] } 50. Rg6 { [%eval 2.07] } 50... a5 { [%eval 2.99] } 51. Rxg5 { [%eval 2.95] } 51... Kc6 { [%eval 2.95] } 52. Kb2 { [%eval 2.85] } 52... Kd5 { [%eval 2.87] } 53. Kb3 { [%eval 2.87] } 53... Kd4 { [%eval 2.77] } 54. Rh5 { [%eval 2.59] } 54... Nc6 { [%eval 3.53] } 55. Ka4 { [%eval 2.32] } 55... Kc4 { [%eval 3.73] } 56. Rh6 { [%eval 3.56] } 56... Kd5 { [%eval 3.46] } 57. Kb5 { [%eval 3.22] } 57... Nxe5 { [%eval 3.21] } 58. Rh5 { [%eval 2.9] } 58... Kd4 { [%eval 4.7] } 59. Kxa5 { [%eval 3.56] } 59... Nd3 { [%eval 8.39] } 60. Kb5 { [%eval 6.87] } 60... e5 { [%eval 8.14] } 61. a4 { [%eval 7.91] } 61... Nf4 { [%eval 15.23] } 62. Rh4 { [%eval 12.08] } 62... Kd5 { [%eval 52.37] } 63. a5 { [%eval 15.53] } 63... Ne6 { [%eval #20] } 64. Rc4 { [%eval 54.6] } *\n\n\n",
      "analysis": [
        {
          "eval": 12
        },
        {
          "eval": 18
        },
        {
          "eval": 15
        },
        {
          "eval": 8
        },
        {
          "eval": 15
        },
        {
          "eval": 0
        },
        {
          "eval": 8
        },
        {
          "eval": 47
        },
        {
          "eval": 17
        },
        {
          "eval": 57
        },
        {
          "eval": 26
        },
        {
          "eval": 35
        },
        {
          "eval": 23
        },
        {
          "eval": 26
        },
        {
          "eval": 50
        },
        {
          "eval": 82
        },
        {
          "eval": 17,
          "best": "g5f6",
          "variation": "Bxf6 gxf6 f4 Bd7 Be2 O-O a3 b5 Nb3 Rb8 Qe3 Kh8 Qh3 Rg8",
          "judgment": {
            "name": "Inaccuracy",
            "comment": "Inaccuracy. Bxf6 was best."
          }
        },
        {
          "eval": 53
        },
        {
          "eval": 8
        },
        {
          "eval": 15
        },
        {
          "eval": 12
        },
        {
          "eval": 31
        },
        {
          "eval": 8
        },
        {
          "eval": 15
        },
        {
          "eval": 0
        },
        {
          "eval": 28
        },
        {
          "eval": -47,
          "best": "f1d3",
          "variation": "Bd3",
          "judgment": {
            "name": "Inaccuracy",
            "comment": "Inaccuracy. Bd3 was best."
          }
        },
        {
          "eval": 10,
          "best": "h7h6",
          "variation": "h6",
          "judgment": {
            "name": "Inaccuracy",
            "comment": "Inaccuracy. h6 was best."
          }
        },
        {
          "eval": -19
        },
        {
          "eval": -12
        },
        {
          "eval": -10
        },
        {
          "eval": 0
        },
        {
          "eval": 0
        },
        {
          "eval": -11
        },
        {
          "eval": -21
        },
        {
          "eval": -9
        },
        {
          "eval": -36
        },
        {
          "eval": -17
        },
        {
          "eval": -39
        },
        {
          "eval": -15
        },
        {
          "eval": -27
        },
        {
          "eval": 35,
          "best": "e6e5",
          "variation": "e5 Nf5 Ree8 Be4 Bxe4 fxe4 Nf6 Ne3 Nxe4 Qg2 Qc6 Nd5 Nf6 Nxf6+",
          "judgment": {
            "name": "Inaccuracy",
            "comment": "Inaccuracy. e5 was best."
          }
        },
        {
          "eval": -60,
          "best": "c2c3",
          "variation": "c3",
          "judgment": {
            "name": "Inaccuracy",
            "comment": "Inaccuracy. c3 was best."
          }
        },
        {
          "eval": -40
        },
        {
          "eval": -43
        },
        {
          "eval": -42
        },
        {
          "eval": -50
        },
        {
          "eval": -9
        },
        {
          "eval": -21
        },
        {
          "eval": -30
        },
        {
          "eval": -43
        },
        {
          "eval": -45
        },
        {
          "eval": -47
        },
        {
          "eval": -32
        },
        {
          "eval": -131,
          "best": "e1e4",
          "variation": "Re4 Ne3 Rxf4 Nxg2 Re4 Rd5 Rd2 f5 exf6 e5 Rxg2 Rxd4 Rxd4 exd4",
          "judgment": {
            "name": "Inaccuracy",
            "comment": "Inaccuracy. Re4 was best."
          }
        },
        {
          "eval": 0,
          "best": "d7d1",
          "variation": "Rxd1+ Rxd1 Kf8 Na7 Re8 Rf1 Rd8 a4 Ne3 Rxf4 Nxg2 Re4 Rd1+ Ka2",
          "judgment": {
            "name": "Mistake",
            "comment": "Mistake. Rxd1+ was best."
          }
        },
        {
          "eval": 0
        },
        {
          "eval": 0
        },
        {
          "eval": 0
        },
        {
          "eval": 0
        },
        {
          "eval": 0
        },
        {
          "eval": 0
        },
        {
          "eval": 0
        },
        {
          "eval": 0
        },
        {
          "eval": 0
        },
        {
          "eval": 0
        },
        {
          "eval": -107,
          "best": "f1g1",
          "variation": "Rg1 Ne2 Rxf7+ Kg8 Rgf1 Nf4 Rg1",
          "judgment": {
            "name": "Inaccuracy",
            "comment": "Inaccuracy. Rg1 was best."
          }
        },
        {
          "eval": 0,
          "best": "h6h3",
          "variation": "Qh3",
          "judgment": {
            "name": "Inaccuracy",
            "comment": "Inaccuracy. Qh3 was best."
          }
        },
        {
          "eval": -60,
          "best": "f1g1",
          "variation": "Rg1 h6 Rh1 h5 Rg1 Nh3 Rf1 Nf4",
          "judgment": {
            "name": "Inaccuracy",
            "comment": "Inaccuracy. Rg1 was best."
          }
        },
        {
          "eval": -44
        },
        {
          "eval": -42
        },
        {
          "eval": 0
        },
        {
          "eval": 0
        },
        {
          "eval": 0
        },
        {
          "eval": 0
        },
        {
          "eval": 0
        },
        {
          "eval": 0
        },
        {
          "eval": 83,
          "best": "b5b4",
          "variation": "b4 c4 bxc3 Kc2 Kg6 Kxc3 h5 Kd4 h4 Ke4 Kh5 Rc1 h3 Kf3",
          "judgment": {
            "name": "Inaccuracy",
            "comment": "Inaccuracy. b4 was best."
          }
        },
        {
          "eval": 54
        },
        {
          "eval": 62
        },
        {
          "eval": 55
        },
        {
          "eval": 125,
          "best": "a6a5",
          "variation": "a5 Kc2 Ke7 Rh1 Kd7 Rg1 g4 Rf1 Nh3 Rf7+ Kc6 Rg7 Kc5 Kd3",
          "judgment": {
            "name": "Inaccuracy",
            "comment": "Inaccuracy. a5 was best."
          }
        },
        {
          "eval": 78
        },
        {
          "eval": 160,
          "best": "f7g6",
          "variation": "Kg6 Kc2",
          "judgment": {
            "name": "Inaccuracy",
            "comment": "Inaccuracy. Kg6 was best."
          }
        },
        {
          "eval": 157
        },
        {
          "eval": 202
        },
        {
          "eval": 195
        },
        {
          "eval": 194
        },
        {
          "eval": 194
        },
        {
          "eval": 216
        },
        {
          "eval": 211
        },
        {
          "eval": 215
        },
        {
          "eval": 215
        },
        {
          "eval": 215
        },
        {
          "eval": 215
        },
        {
          "eval": 214
        },
        {
          "eval": 207
        },
        {
          "eval": 214
        },
        {
          "eval": 207
        },
        {
          "eval": 299,
          "best": "b4d3",
          "variation": "Nd3 Rxg5 Kc6 Kc2 Nc5 Rh5 Kd5 Kc3 a5 Rh8 Ne4+ Kd3 Nc5+ Kc2",
          "judgment": {
            "name": "Inaccuracy",
            "comment": "Inaccuracy. Nd3 was best."
          }
        },
        {
          "eval": 295
        },
        {
          "eval": 295
        },
        {
          "eval": 285
        },
        {
          "eval": 287
        },
        {
          "eval": 287
        },
        {
          "eval": 277
        },
        {
          "eval": 259
        },
        {
          "eval": 353,
          "best": "b4d5",
          "variation": "Nd5 Rh4+",
          "judgment": {
            "name": "Inaccuracy",
            "comment": "Inaccuracy. Nd5 was best."
          }
        },
        {
          "eval": 232
        },
        {
          "eval": 373,
          "best": "c6b4",
          "variation": "Nb4 Rh2",
          "judgment": {
            "name": "Inaccuracy",
            "comment": "Inaccuracy. Nb4 was best."
          }
        },
        {
          "eval": 356
        },
        {
          "eval": 346
        },
        {
          "eval": 322
        },
        {
          "eval": 321
        },
        {
          "eval": 290
        },
        {
          "eval": 470,
          "best": "d5d6",
          "variation": "Kd6 Kxa5",
          "judgment": {
            "name": "Mistake",
            "comment": "Mistake. Kd6 was best."
          }
        },
        {
          "eval": 356
        },
        {
          "eval": 839,
          "best": "e5c4",
          "variation": "Nc4+ Kb4",
          "judgment": {
            "name": "Blunder",
            "comment": "Blunder. Nc4+ was best."
          }
        },
        {
          "eval": 687
        },
        {
          "eval": 814,
          "best": "d3f4",
          "variation": "Nf4"
        },
        {
          "eval": 791
        },
        {
          "eval": 1523,
          "best": "e5e4",
          "variation": "e4 a5 e3 Rh4+ Ke5 a6 e2 Rh1 e1=Q Rxe1+ Nxe1 a7 Nf3 a8=Q"
        },
        {
          "eval": 1208
        },
        {
          "eval": 5237
        },
        {
          "eval": 1553
        },
        {
          "mate": 20,
          "best": "f4g6",
          "variation": "Ng6 Rh1 Nf4 a6 Ne6 Kb6 Kc4 a7 Nf4 a8=Q Nd5+ Kb7 Nc3 Qc8+",
          "judgment": {
            "name": "Inaccuracy",
            "comment": "Checkmate is now unavoidable. Ng6 was best."
          }
        },
        {
          "eval": 5460
        }
      ],
      "division": {
        "middle": 22,
        "end": 58
      }
    }
  ]
}