{
  "_id": "wnxtW-juKrY",
  "videoSnippet": {
    "schemaVersion": 1,
    "retrievedAt": "2023-02-12T19:40:52.272Z",
    "publishedAt": "2020-10-15T12:46:13Z",
    "title": "Monster and His Knight || Carlsen vs Tari || Altibox Norway Chess (2020)",
    "description": "IMPORTANT! Follow Age of Caissa here https://twitter.com/AgeOfCaissa\nRead Chapter 1 of Age of Caissa Here https://agadmator.com/mangach1\n \nMagnus Carlsen vs Aryan Tari\nAltibox Norway Chess (2020) \n13.10.2020\nRuy Lopez, closed defence (C84)\n\n1. e4 e5 2. Nf3 Nc6 3. Bb5 a6 4. Ba4 Nf6 5. O-O Be7 6. d3 b5 7. Bb3 d6 8. a4 Bd7 9. c3 Na5 10. Ba2 c5 11. Bg5 O-O 12. Nbd2 Rb8 13. axb5 axb5 14. Re1 b4 15. Nc4 Nxc4 16. Bxc4 bxc3 17. bxc3 Qc7 18. Qc2 Bb5 19.  Bxb5  Rxb5 20.  Bxf6  Bxf6 21.  Nd2  Qc6 22.  Qa4  Rfb8 23.  Nc4  Be7 24.  G3  Qc8 25.  Qd1  G6 26.  Kg2  Bf8 27.  Qf3  Rb3 28.  Rec1  Qe6 29.  Ra7  R8b7 30.  Rxb7  Rxb7 31 .  Ra1  h5 - 32.  Ra8  Kg7 33.  Ne3  Rc7 34.  Nd5  Rc8 35.  Ra7  Rb8   37. g4    39. Ra8 f6  f5  Rf7 42. Re8 Qxe8  Kg8  Kh8 45.  Nf6\n\nCheck out agadmator's merch here https://teespring.com/stores/agadmators-swag-store\nhttps://teespring.com/design-with-a-story-tm\n\nMailbox where you can send stuff:\n\nAntonio Radić\nAGADMATOR d.o.o.\nFranje Tuđmana 12\nCroatia\n48260 Križevci \np.s. this is not my home address :)\n\nContact me: agadmatormanga@gmail.com or agadmator@gmail.com \n\nDownload agadmator chess clock for iOS here https://apps.apple.com/us/app/agadmator-chess-clock/id1474461379?ls=1&fbclid=IwAR2lhuxf60tpbW1vcvfXgdFzmShi6fHcrKxFF_NAhu9wLQwpJrAFbMWRYjk\n\nDownload agadmator chess clock for Android here https://play.google.com/store/apps/details?id=com.agadmator.chessclock&fbclid=IwAR3b_sRch6nsuW59-bWoirVDMMJ8V5jexZdUB0bsxQrc0Q8imvkBtqkHUXQ&rdid=com.agadmator.chessclock\n\nSupport fishnet here https://lichess.org/get-fishnet\n\nVideo created by OBS\n\n----------------------------------------------------------------------------------------------------------------------------------------\nIf you realllly enjoy my content, you're welcome to support me and my channel with a small donation via PayPal or Crypto.\n\nLink to PayPal donation https://www.paypal.me/agadmator\n\nNEW: You can now become a MEMBER of agadmator's Chess Channel https://www.youtube.com/channel/UCL5YbN5WLFD8dLIegT5QAbA/join\n\nCrypto handle @agadmator\nBTC address 3J7WigeEa95mNtZ8yJ26BBYexNz4r7XAUH\nBCH address qzx5tu8uelq7s4tavsnk628f2t2s3g8gdvvnvcrvuq\nLTC address MDrZdNjZm7btVkuLRdtrge9rwZn5TtjppM\nETH address 0x7a80bD0BF9c8e4B98afd43954fd9Df8e4a600245\nNano \n\nCheck out some of the books I enjoy https://www.amazon.com/ideas/amzn1.account.AFWWCIBWCL5PGEPL73FDWK632F7Q/2QAGBMLVXE7MG\n\nCheck out ALL my videos here https://www.youtube.com/watch?v=fYgd5ZLdHz8&list=PLDnx7w_xuguFTxcfiM11bB1JchtHclEJg\n\nFacebook: https://www.facebook.com/agadmatoryoutube\nTwitter: https://twitter.com/agadmator\nInstagram: https://www.instagram.com/agadmator/\nLichess: https://lichess.org/@/agadmator\nChess.com: agadmator\nLeague of Legends: agadmator (EUNE, my friend is using my EUWE account for a couple of years now)\nBlizzard: agadmator #2992 \nJoin our Discord Server here https://discord.gg/bY6BbRP\n\n#NorwayChess",
    "thumbnail": {
      "default": {
        "url": "https://i.ytimg.com/vi/wnxtW-juKrY/default.jpg",
        "width": 120,
        "height": 90
      },
      "medium": {
        "url": "https://i.ytimg.com/vi/wnxtW-juKrY/mqdefault.jpg",
        "width": 320,
        "height": 180
      },
      "high": {
        "url": "https://i.ytimg.com/vi/wnxtW-juKrY/hqdefault.jpg",
        "width": 480,
        "height": 360
      },
      "standard": {
        "url": "https://i.ytimg.com/vi/wnxtW-juKrY/sddefault.jpg",
        "width": 640,
        "height": 480
      },
      "maxres": {
        "url": "https://i.ytimg.com/vi/wnxtW-juKrY/maxresdefault.jpg",
        "width": 1280,
        "height": 720
      }
    },
    "videoId": "wnxtW-juKrY"
  },
  "videoGame": [
    {
      "playerWhite": "Magnus Carlsen",
      "playerBlack": "Aryan Tari",
      "date": "2020-10-13"
    }
  ],
  "videoContentDetails": {
    "duration": "PT16M5S"
  },
  "stockfishEval": [
    null
  ],
  "lichessGameId": [
    {}
  ],
  "lichessGameEval": [
    {}
  ]
}